z3c.layer.pagelet-3.0-py3.9-nspkg.pth
z3c/layer/pagelet/README.rst
z3c/layer/pagelet/__init__.py
z3c/layer/pagelet/configure.zcml
z3c/layer/pagelet/interfaces.py
z3c/layer/pagelet/testing.py
z3c/layer/pagelet/z3c.layer.pagelet-configure.zcml
z3c/layer/pagelet/zope.app.publication.zcml
z3c/layer/pagelet/zope.browserresource.zcml
z3c/layer/pagelet/zope.traversing.browser.zcml
z3c/layer/pagelet/zope.traversing.zcml
z3c/layer/pagelet/browser/__init__.py
z3c/layer/pagelet/browser/configure.zcml
z3c/layer/pagelet/browser/notfound.pt
z3c/layer/pagelet/browser/systemerror.pt
z3c/layer/pagelet/browser/unauthorized.pt
z3c/layer/pagelet/browser/user.pt
z3c/layer/pagelet/tests/__init__.py
z3c/layer/pagelet/tests/bugfixes.rst
z3c/layer/pagelet/tests/ftesting.zcml
z3c/layer/pagelet/tests/page.pt
z3c/layer/pagelet/tests/template.pt
z3c/layer/pagelet/tests/test_exception_views.py
z3c/layer/pagelet/tests/test_layer.py
z3c.layer.pagelet-3.0.dist-info/LICENSE.txt
z3c.layer.pagelet-3.0.dist-info/METADATA
z3c.layer.pagelet-3.0.dist-info/WHEEL
z3c.layer.pagelet-3.0.dist-info/namespace_packages.txt
z3c.layer.pagelet-3.0.dist-info/top_level.txt
z3c.layer.pagelet-3.0.dist-info/RECORD
