Metadata-Version: 2.1
Name: z3c.layer.pagelet
Version: 3.0
Summary: Pagelet layer setup for Zope 3
Home-page: https://github.com/zopefoundation/z3c.layer.pagelet
Author: Zope Foundation and Contributors
Author-email: zope-dev@zope.dev
License: ZPL 2.1
Keywords: z3c pagelet layer zope zope3
Classifier: Development Status :: 5 - Production/Stable
Classifier: Environment :: Web Environment
Classifier: Intended Audience :: Developers
Classifier: License :: OSI Approved :: Zope Public License
Classifier: Programming Language :: Python
Classifier: Programming Language :: Python :: 3
Classifier: Programming Language :: Python :: 3.7
Classifier: Programming Language :: Python :: 3.8
Classifier: Programming Language :: Python :: 3.9
Classifier: Programming Language :: Python :: 3.10
Classifier: Programming Language :: Python :: 3.11
Classifier: Programming Language :: Python :: Implementation :: CPython
Classifier: Natural Language :: English
Classifier: Operating System :: OS Independent
Classifier: Topic :: Internet :: WWW/HTTP
Classifier: Framework :: Zope :: 3
Requires-Python: >=3.7
License-File: LICENSE.txt
Requires-Dist: setuptools
Requires-Dist: z3c.pagelet
Requires-Dist: z3c.template
Requires-Dist: zope.authentication
Requires-Dist: zope.browser (>=1.2)
Requires-Dist: zope.browserresource
Requires-Dist: zope.component
Requires-Dist: zope.interface
Requires-Dist: zope.login
Requires-Dist: zope.publisher (>=3.12)
Provides-Extra: test
Requires-Dist: WebTest ; extra == 'test'
Requires-Dist: zope.app.wsgi (>=3.8) ; extra == 'test'
Requires-Dist: zope.exceptions ; extra == 'test'
Requires-Dist: zope.principalregistry ; extra == 'test'
Requires-Dist: zope.publisher ; extra == 'test'
Requires-Dist: zope.security ; extra == 'test'
Requires-Dist: zope.securitypolicy ; extra == 'test'
Requires-Dist: zope.testing ; extra == 'test'
Requires-Dist: zope.testrunner ; extra == 'test'
